genevol/__init__.py
genevol-0.0.0.dist-info/LICENSE
genevol-0.0.0.dist-info/METADATA
genevol-0.0.0.dist-info/WHEEL
genevol-0.0.0.dist-info/top_level.txt
genevol-0.0.0.dist-info/RECORD
