Metadata-Version: 2.1
Name: genevol
Version: 0.0.0
Summary: Genevol - Genetic and Evolutionary Algorithms
Home-page: UNKNOWN
Author: Prabhat Nagarajan
Author-email: prabhat@prabhatnagarajan.com
License: MIT License
Platform: UNKNOWN
Requires-Dist: cached-property
Requires-Dist: gym (>=0.9.7)
Requires-Dist: numpy (>=1.10.4)
Requires-Dist: pillow
Requires-Dist: scipy
